rtasp/__init__.py
rtasp/__main__.py
rtasp/_version.py
rtasp/config/__init__.py
rtasp-0.1.7.dist-info/licenses/LICENSE
rtasp-0.1.7.dist-info/METADATA
rtasp-0.1.7.dist-info/WHEEL
rtasp-0.1.7.dist-info/top_level.txt
rtasp-0.1.7.dist-info/RECORD
