Metadata-Version: 2.4
Name: rtasp
Version: 0.1.7
Summary: libs to run RTASP  - Real-Time Annotation and Stream Processing 
Home-page: https://python.rtasp.com
Author: Tom Sapletta
Author-email: tom@sapletta.com
Maintainer: rtasp developers
Maintainer-email: info@softreck.dev
License: Apache-2.0
Project-URL: Repository, https://github.com/rt-asp/python
Project-URL: Changelog, https://github.com/rt-asp/python/releases
Project-URL: Wiki, https://github.com/rt-asp/python/wiki
Project-URL: Issue Tracker, https://github.com/rt-asp/python/issues/new
Keywords: python,rtasp,markdown,app,python,markdown,app,streaming,real-time
Classifier: License :: OSI Approved :: Apache Software License
Classifier: Programming Language :: Python
Classifier: Programming Language :: Python :: 3
Classifier: Programming Language :: Python :: 3.7
Classifier: Programming Language :: Python :: 3.8
Classifier: Programming Language :: Python :: 3.9
Classifier: Programming Language :: Python :: 3.10
Classifier: Programming Language :: Python :: 3.11
Requires-Python: >=3.7
License-File: LICENSE
Dynamic: author
Dynamic: author-email
Dynamic: classifier
Dynamic: description
Dynamic: description-content-type
Dynamic: home-page
Dynamic: keywords
Dynamic: license
Dynamic: license-file
Dynamic: maintainer
Dynamic: maintainer-email
Dynamic: project-url
Dynamic: requires-python
Dynamic: summary
